{
  "format": "single_session",
  "ryan": {
    "class": "F Street",
    "runs": [
      {
        "run_number": 1,
        "session": "a",
        "displayed_time": 48.65,
        "cones": 0,
        "base_time": 48.65,
        "scored_time": 48.65,
        "dnf": false,
        "rerun": false
      },
      {
        "run_number": 2,
        "session": "a",
        "displayed_time": 48.048,
        "cones": 0,
        "base_time": 48.048,
        "scored_time": 48.048,
        "dnf": false,
        "rerun": false
      },
      {
        "run_number": 3,
        "session": "a",
        "displayed_time": 45.744,
        "cones": 0,
        "base_time": 45.744,
        "scored_time": 45.744,
        "dnf": false,
        "rerun": false
      },
      {
        "run_number": 4,
        "session": "a",
        "displayed_time": 45.319,
        "cones": 0,
        "base_time": 45.319,
        "scored_time": 45.319,
        "dnf": false,
        "rerun": false
      },
      {
        "run_number": 5,
        "session": "a",
        "displayed_time": 49.624,
        "cones": 1,
        "base_time": 47.624,
        "scored_time": 49.624,
        "dnf": false,
        "rerun": false
      },
      {
        "run_number": 6,
        "session": "a",
        "displayed_time": 45.319,
        "cones": 0,
        "base_time": 45.319,
        "scored_time": 45.319,
        "dnf": false,
        "rerun": false
      }
    ]
  },
  "cars": [
    {
      "name": "Alexandra Zust",
      "car": "2018 Porsche GT3"
    },
    {
      "name": "Bryan Wofford",
      "car": "2023 Tesla Model Y"
    },
    {
      "name": "Curtis Staples",
      "car": "2014 Porsche Cayman S"
    },
    {
      "name": "Cobey Riley",
      "car": "2020 Toyota GR Supra"
    },
    {
      "name": "Oliver Geiger",
      "car": "2015 Mazda Miata"
    },
    {
      "name": "Nathan Streiff",
      "car": "2020 Subaru BRZ"
    },
    {
      "name": "Joseph Harding",
      "car": "2022 Subaru WRX"
    },
    {
      "name": "Frederick Drescher",
      "car": "1994 Mazda Miata"
    },
    {
      "name": "Jack Brinkley",
      "car": "2005 Mazda Miata"
    },
    {
      "name": "Ryan Berg",
      "car": "2022 BMW M240i"
    },
    {
      "name": "Nicholas Rogowski",
      "car": "2011 BMW M3"
    },
    {
      "name": "David Perry",
      "car": "2016 Volkswagen GTI"
    },
    {
      "name": "Ross Hennings",
      "car": "2015 Ford Fiesta ST"
    },
    {
      "name": "Emily Huneycutt",
      "car": "2019 Honda Civic Sport"
    },
    {
      "name": "Philip Turner",
      "car": "1974 MG"
    },
    {
      "name": "Felipe Pipe Monserrate",
      "car": "1974 Porsche 914"
    },
    {
      "name": "Dave Scherpf",
      "car": "2011 BMW 128i"
    },
    {
      "name": "Diaz McDaniel",
      "car": "2018 Audi RS3"
    },
    {
      "name": "Ernie Torres",
      "car": "2017 Subaru WRX"
    },
    {
      "name": "Matthew Weatherly",
      "car": "2022 Hyundai Elantra N"
    },
    {
      "name": "Jeremy Wilhelm",
      "car": "2022 Hyundai Elantra N"
    },
    {
      "name": "Brian Garman",
      "car": "1991 Mazda Miata"
    },
    {
      "name": "Robby Helms",
      "car": "1988 Honda CRX Si"
    },
    {
      "name": "Peter Lockett",
      "car": "2019 Mazda MX5"
    },
    {
      "name": "Randall Wilcox",
      "car": "2012 Volkswagen Golf"
    },
    {
      "name": "Phillip Prewitt",
      "car": "2010 Subaru STI"
    },
    {
      "name": "Cameron Kramer",
      "car": "2018 Golf R"
    },
    {
      "name": "John Byrd",
      "car": "2022 Subaru WRX"
    },
    {
      "name": "Mitchell Poalillo",
      "car": "2002 Honda S2000"
    },
    {
      "name": "Scott Halligan",
      "car": "2004 Honda S2000"
    },
    {
      "name": "Drew Thompson",
      "car": "2006 Honda S2000"
    },
    {
      "name": "Chris Murray",
      "car": "2020 Toyota Supra"
    },
    {
      "name": "William Huneycutt",
      "car": "1995 Mazda Miata"
    },
    {
      "name": "Glenn Sobrian",
      "car": "2016 Audi S5"
    },
    {
      "name": "Derek Secord",
      "car": "2006 Chevrolet Corvette Z06"
    },
    {
      "name": "Mike New",
      "car": "2006 Chevrolet Corvette Z06"
    },
    {
      "name": "Michael Roger",
      "car": "1980 Chevrolet Malibu"
    },
    {
      "name": "Scott Johns",
      "car": "2019 Chevrolet Corvette"
    },
    {
      "name": "David Grainger",
      "car": "2020 Ford Mustang Mach 1"
    },
    {
      "name": "Wes Enfinger",
      "car": "2020 Ford Mustang Mach 1"
    },
    {
      "name": "Dustin Sightler",
      "car": "2001 Chevrolet Corvette"
    },
    {
      "name": "Mark Grant",
      "car": "Dodge Challenger SRT8"
    },
    {
      "name": "Chris Kemper",
      "car": "2003 Chevrolet Corvette Z06"
    },
    {
      "name": "Grant Skidmore",
      "car": "1997 Jeep Cherokee"
    },
    {
      "name": "Mike Fowke",
      "car": "1978 Pontiac Firebird"
    },
    {
      "name": "Mark Alascio",
      "car": "2001 Chevrolet Corvette Z06"
    },
    {
      "name": "Tripp Bouknight",
      "car": "1980 Chevrolet Malibu"
    },
    {
      "name": "Rhyon Teller",
      "car": "1997 Chevrolet S10"
    },
    {
      "name": "Terry Grant",
      "car": "2014 Dodge RAM 1500"
    },
    {
      "name": "Mark Sightler",
      "car": "2001 Chevrolet Corvette"
    },
    {
      "name": "Fred Zust",
      "car": "2005 Lotus Elise"
    },
    {
      "name": "Gregory Gorrell",
      "car": "2000 Porsche Boxster S"
    },
    {
      "name": "Scott Good",
      "car": "2000 Porsche Boxster S"
    },
    {
      "name": "Nathan Brainerd",
      "car": "1988 Volkswagen Scirocco"
    },
    {
      "name": "Tim Matijow",
      "car": "1991 Toyota MR2"
    },
    {
      "name": "Jon Furr",
      "car": "1983 Volkswagen GTI"
    },
    {
      "name": "Ross Pendergast-Pedersen",
      "car": "2008 Subaru STI"
    },
    {
      "name": "Andy Groce",
      "car": "1999 Mazda Miata"
    },
    {
      "name": "W Dean Furr",
      "car": "1983 Volkswagen GTI"
    },
    {
      "name": "John Hinton",
      "car": "1991 Toyota MR2"
    },
    {
      "name": "Joshua Elks",
      "car": "2006 Mazda MX5"
    },
    {
      "name": "Kathy Groce",
      "car": "1999 Mazda Miata"
    },
    {
      "name": "Jeffrey King",
      "car": "2014 Honda Civic Si"
    },
    {
      "name": "Tony Wellinghurst",
      "car": "1983 Volkswagen GTI"
    },
    {
      "name": "Kevin Wofford",
      "car": "2019 Ford Mustang"
    },
    {
      "name": "Jonathan Mudge",
      "car": "2013 Scion FR-S"
    },
    {
      "name": "Kevin Wenzel",
      "car": "2007 Chevrolet Corvette Z06"
    },
    {
      "name": "Rajat Aggarwal",
      "car": "2019 Honda Civic Si"
    },
    {
      "name": "Nick Latronica",
      "car": "2021 Mazda MX5"
    },
    {
      "name": "Joseph Price",
      "car": "2022 Subaru BRZ"
    },
    {
      "name": "Jeffrey Harris",
      "car": "2021 Mazda Miata"
    },
    {
      "name": "Connor Placer",
      "car": "2016 Mazda MX-5 Miata"
    },
    {
      "name": "Harlan Williams",
      "car": "1999 Mazda Miata"
    },
    {
      "name": "Ryan Callari",
      "car": "2022 Tesla Model 3"
    },
    {
      "name": "Donna Littlejohn",
      "car": "2007 Chevrolet Corvette Z06"
    },
    {
      "name": "Jonathan Bennett",
      "car": "1990 Honda CRX"
    },
    {
      "name": "Jacques Bene",
      "car": "1993 Mazda Biscuit"
    },
    {
      "name": "John Fink",
      "car": "2019 Chevrolet Corvette"
    },
    {
      "name": "George Bene",
      "car": "1993 Mazda Biscuit"
    },
    {
      "name": "John Robison",
      "car": "2001 BMW 330ci"
    },
    {
      "name": "Colton Holt",
      "car": "2015 BMW M4"
    },
    {
      "name": "Khalif Thomas",
      "car": "2007 Honda Civic Si"
    },
    {
      "name": "Sam Evans",
      "car": "2006 Mazda Miata"
    },
    {
      "name": "Doug Bennett",
      "car": "1990 Honda CRX"
    },
    {
      "name": "Randy Cogburn",
      "car": "2008 Chevrolet Corvette"
    },
    {
      "name": "John Kelly",
      "car": "2004 Porsche 911 C2 CAB"
    },
    {
      "name": "Jean Markowski",
      "car": "1974 MG B"
    },
    {
      "name": "James Gunnels",
      "car": "2008 Honda Civic Si"
    },
    {
      "name": "Ryan Shelton",
      "car": "2016 Mazda Miata"
    },
    {
      "name": "Ryan Bischetsrieder",
      "car": "2016 Volkswagen Golf GTI"
    },
    {
      "name": "John Samuel",
      "car": "2017 Volkswagen Golf GTI"
    },
    {
      "name": "Grimshaw Austin",
      "car": "2011 Chevrolet Camaro"
    },
    {
      "name": "Tristan Stephens",
      "car": "2004 Mazda RX8"
    },
    {
      "name": "Tony Zsigmond",
      "car": "2008 Honda Fit"
    },
    {
      "name": "Kandy Reyes",
      "car": "2016 Ford Focus RS"
    },
    {
      "name": "Clay Swindler",
      "car": "2003 Acura RSX"
    },
    {
      "name": "Asa Pranikoff",
      "car": "2018 Subaru WRX STI"
    },
    {
      "name": "Daylan Shubert",
      "car": "2017 Volkswagen Golf GTI"
    },
    {
      "name": "Jonathan Chapman",
      "car": "1989 Rover Mini"
    },
    {
      "name": "Noah Hicks",
      "car": "2001 Chevrolet Corvette"
    },
    {
      "name": "Arthur Honer",
      "car": "2013 Mini Mini Cooper"
    },
    {
      "name": "Kurt Fernandes",
      "car": "2017 Toyota GT86"
    },
    {
      "name": "Mike Casino",
      "car": "2022 Subaru BRZ"
    },
    {
      "name": "L James Farris",
      "car": "1974 MG B"
    },
    {
      "name": "Jeffrey Haas",
      "car": "1992 Mazda Miata"
    },
    {
      "name": "Matt Klein",
      "car": "2003 Chevrolet Corvette Z06"
    },
    {
      "name": "Michael Shoolbred",
      "car": "1997 Mazda Miata"
    },
    {
      "name": "Rebekah Sightler",
      "car": "2015 Subaru BRZ"
    },
    {
      "name": "Jeremy Stewart",
      "car": "2017 Toyota 86"
    },
    {
      "name": "Chris Whittaker",
      "car": "2010 Honda Civic"
    }
  ]
}